easynetwork/__init__.py
easynetwork/_typevars.py
easynetwork/converter.py
easynetwork/exceptions.py
easynetwork/protocol.py
easynetwork/py.typed
easynetwork/version.py
easynetwork/warnings.py
easynetwork/clients/__init__.py
easynetwork/clients/_base.py
easynetwork/clients/_iter.py
easynetwork/clients/abc.py
easynetwork/clients/async_tcp.py
easynetwork/clients/async_udp.py
easynetwork/clients/async_unix_datagram.py
easynetwork/clients/async_unix_stream.py
easynetwork/clients/tcp.py
easynetwork/clients/udp.py
easynetwork/clients/unix_datagram.py
easynetwork/clients/unix_stream.py
easynetwork/lowlevel/__init__.py
easynetwork/lowlevel/_errno.py
easynetwork/lowlevel/_final.py
easynetwork/lowlevel/_lock.py
easynetwork/lowlevel/_stream.py
easynetwork/lowlevel/_unix_utils.py
easynetwork/lowlevel/_utils.py
easynetwork/lowlevel/constants.py
easynetwork/lowlevel/futures.py
easynetwork/lowlevel/socket.py
easynetwork/lowlevel/typed_attr.py
easynetwork/lowlevel/api_async/__init__.py
easynetwork/lowlevel/api_async/backend/__init__.py
easynetwork/lowlevel/api_async/backend/abc.py
easynetwork/lowlevel/api_async/backend/utils.py
easynetwork/lowlevel/api_async/backend/_asyncio/__init__.py
easynetwork/lowlevel/api_async/backend/_asyncio/_asyncio_utils.py
easynetwork/lowlevel/api_async/backend/_asyncio/_flow_control.py
easynetwork/lowlevel/api_async/backend/_asyncio/backend.py
easynetwork/lowlevel/api_async/backend/_asyncio/dns_resolver.py
easynetwork/lowlevel/api_async/backend/_asyncio/tasks.py
easynetwork/lowlevel/api_async/backend/_asyncio/threads.py
easynetwork/lowlevel/api_async/backend/_asyncio/datagram/__init__.py
easynetwork/lowlevel/api_async/backend/_asyncio/datagram/endpoint.py
easynetwork/lowlevel/api_async/backend/_asyncio/datagram/listener.py
easynetwork/lowlevel/api_async/backend/_asyncio/datagram/socket.py
easynetwork/lowlevel/api_async/backend/_asyncio/stream/__init__.py
easynetwork/lowlevel/api_async/backend/_asyncio/stream/listener.py
easynetwork-1.1.4.dist-info/METADATA
easynetwork-1.1.4.dist-info/WHEEL
easynetwork-1.1.4.dist-info/licenses/LICENSE
easynetwork-1.1.4.dist-info/RECORD
