Metadata-Version: 2.4
Name: easynetwork
Version: 1.1.4
Summary: The easiest way to use sockets in Python
Project-URL: Documentation, https://easynetwork.readthedocs.io/
Project-URL: Issue Tracker, https://github.com/francis-clairicia/EasyNetwork/issues
Project-URL: Release Notes, https://github.com/francis-clairicia/EasyNetwork/releases
Project-URL: Source Code, https://github.com/francis-clairicia/EasyNetwork
Author-email: FrankySnow9 <clairicia.rcj.francis@gmail.com>
License-File: LICENSE
Keywords: async,asynchronous,client,communication,networking,serialization,server,socket
Classifier: Development Status :: 5 - Production/Stable
Classifier: Framework :: AsyncIO
Classifier: Intended Audience :: Developers
Classifier: License :: OSI Approved :: Apache Software License
Classifier: Operating System :: MacOS
Classifier: Operating System :: Microsoft :: Windows
Classifier: Operating System :: POSIX :: BSD
Classifier: Operating System :: POSIX :: Linux
Classifier: Programming Language :: Python :: 3 :: Only
Classifier: Programming Language :: Python :: 3.11
Classifier: Programming Language :: Python :: 3.12
Classifier: Programming Language :: Python :: 3.13
Classifier: Topic :: Internet
Classifier: Topic :: Software Development :: Libraries :: Python Modules
Classifier: Topic :: System :: Networking
Classifier: Typing :: Typed
Requires-Python: >=3.11
Requires-Dist: sniffio<2,>=1.3.1
Provides-Extra: cbor
Requires-Dist: cbor2<6,>=5.5; extra == 'cbor'
Provides-Extra: msgpack
Requires-Dist: msgpack<2,>=1.1.0; extra == 'msgpack'
Provides-Extra: trio
Requires-Dist: outcome~=1.3; extra == 'trio'
Requires-Dist: trio<1,>=0.26; extra == 'trio'
